[{"name": "Capital goods", "path": "Capital goods", "value": 15235567.05}, {"name": "Consumer goods", "path": "Consumer goods", "value": 6810176.434}, {"name": "Intermediate goods", "path": "Intermediate goods", "value": 9990628.657}, {"name": "Mach and Elec", "path": "Mach and Elec", "value": 14869181.95}, {"name": "Metals", "path": "Metals", "value": 1912259.915}, {"name": "Miscellaneous", "path": "Miscellaneous", "value": 1496839.007}, {"name": "Plastic or Rubber", "path": "Plastic or Rubber", "value": 3952114.059}]