[{"name": "Capital goods", "path": "Capital goods", "value": 4733197.55}, {"name": "Consumer goods", "path": "Consumer goods", "value": 3496951.94}, {"name": "Intermediate goods", "path": "Intermediate goods", "value": 1670643.138}, {"name": "Mach and Elec", "path": "Mach and Elec", "value": 4899875.752}, {"name": "Metals", "path": "Metals", "value": 1101301.595}, {"name": "Miscellaneous", "path": "Miscellaneous", "value": 677259.206}, {"name": "Plastic or Rubber", "path": "Plastic or Rubber", "value": 388671.123}]