[{"name": "Capital goods", "path": "Capital goods", "value": 271564.61}, {"name": "Consumer goods", "path": "Consumer goods", "value": 965538.63}, {"name": "Intermediate goods", "path": "Intermediate goods", "value": 1280266.1}, {"name": "Mach and Elec", "path": "Mach and Elec", "value": 125431.12}, {"name": "Metals", "path": "Metals", "value": 934560.58}, {"name": "Miscellaneous", "path": "Miscellaneous", "value": 139531.63}, {"name": "Plastic or Rubber", "path": "Plastic or Rubber", "value": 45947.44}]