[{"name": "Capital goods", "path": "Capital goods", "value": 5371119.010000001}, {"name": "Consumer goods", "path": "Consumer goods", "value": 9263760.23}, {"name": "Intermediate goods", "path": "Intermediate goods", "value": 24564817.430000003}, {"name": "Mach and Elec", "path": "Mach and Elec", "value": 3740100.9799999995}, {"name": "Metals", "path": "Metals", "value": 10078974.150000002}, {"name": "Miscellaneous", "path": "Miscellaneous", "value": 1739917.8599999999}, {"name": "Plastic or Rubber", "path": "Plastic or Rubber", "value": 702087.1}]