[{"name": "Capital goods", "path": "Capital goods", "value": 3.338603024}, {"name": "Consumer goods", "path": "Consumer goods", "value": 748.610156}, {"name": "Intermediate goods", "path": "Intermediate goods", "value": 3.770368501}, {"name": "Mach and Elec", "path": "Mach and Elec", "value": 3.188863742}, {"name": "Metals", "path": "Metals", "value": 302.3728238}, {"name": "Miscellaneous", "path": "Miscellaneous", "value": 141.6429508}, {"name": "Plastic or Rubber", "path": "Plastic or Rubber", "value": 0.39513429}]