[{"name": "Plastic or Rubber", "path": "Plastic or Rubber", "value": 1132764.199}, {"name": "Miscellaneous", "path": "Miscellaneous", "value": 1760638.573}, {"name": "Metals", "path": "Metals", "value": 3948353.061}, {"name": "Mach and Elec", "path": "Mach and Elec", "value": 6197129.008}, {"name": "Capital goods", "path": "Capital goods", "value": 6408588.496}, {"name": "Intermediate goods", "path": "Intermediate goods", "value": 7674851.877}, {"name": "Consumer goods", "path": "Consumer goods", "value": 8777480.502}]