[{"name": "Consumer goods", "path": "Consumer goods", "value": 812417.211}, {"name": "Intermediate goods", "path": "Intermediate goods", "value": 2900.357}, {"name": "Mach and Elec", "path": "Mach and Elec", "value": 45208.392}, {"name": "Metals", "path": "Metals", "value": 532.751}, {"name": "Miscellaneous", "path": "Miscellaneous", "value": 13939.806}, {"name": "Plastic or Rubber", "path": "Plastic or Rubber", "value": 6323.416}, {"name": "Capital goods", "path": "Capital goods", "value": 11272.217}]