[{"name": "Capital goods", "path": "Capital goods", "value": 5043403.699999999}, {"name": "Consumer goods", "path": "Consumer goods", "value": 10505249.26}, {"name": "Intermediate goods", "path": "Intermediate goods", "value": 19435249.82}, {"name": "Mach and Elec", "path": "Mach and Elec", "value": 3414049.13}, {"name": "Metals", "path": "Metals", "value": 7993094.0200000005}, {"name": "Miscellaneous", "path": "Miscellaneous", "value": 39223660.37}, {"name": "Plastic or Rubber", "path": "Plastic or Rubber", "value": 685623.75}]