[{"name": "Capital goods", "path": "Capital goods", "value": 994731.43}, {"name": "Consumer goods", "path": "Consumer goods", "value": 5393496.55}, {"name": "Intermediate goods", "path": "Intermediate goods", "value": 1089106.21}, {"name": "Mach and Elec", "path": "Mach and Elec", "value": 875449.41}, {"name": "Metals", "path": "Metals", "value": 580382.0}, {"name": "Miscellaneous", "path": "Miscellaneous", "value": 85507.51}, {"name": "Plastic or Rubber", "path": "Plastic or Rubber", "value": 317649.89}]