[{"name": "Consumer goods", "path": "Consumer goods", "value": 1466887.652}, {"name": "Intermediate goods", "path": "Intermediate goods", "value": 286208.3339}, {"name": "Mach and Elec", "path": "Mach and Elec", "value": 557627.9104}, {"name": "Metals", "path": "Metals", "value": 56003.02162}, {"name": "Miscellaneous", "path": "Miscellaneous", "value": 112114.2292}, {"name": "Plastic or Rubber", "path": "Plastic or Rubber", "value": 75708.68345}, {"name": "Capital goods", "path": "Capital goods", "value": 673520.8509}]