[{"name": "Capital goods", "path": "Capital goods", "value": 53823.494}, {"name": "Consumer goods", "path": "Consumer goods", "value": 355268.857}, {"name": "Intermediate goods", "path": "Intermediate goods", "value": 80845.784}, {"name": "Mach and Elec", "path": "Mach and Elec", "value": 56123.686}, {"name": "Metals", "path": "Metals", "value": 31575.407}, {"name": "Miscellaneous", "path": "Miscellaneous", "value": 20697.718}, {"name": "Plastic or Rubber", "path": "Plastic or Rubber", "value": 27454.456}]