[{"name": "Capital goods", "path": "Capital goods", "value": 343503.708}, {"name": "Consumer goods", "path": "Consumer goods", "value": 132094.949}, {"name": "Intermediate goods", "path": "Intermediate goods", "value": 267814.606}, {"name": "Mach and Elec", "path": "Mach and Elec", "value": 251350.872}, {"name": "Metals", "path": "Metals", "value": 152193.529}, {"name": "Miscellaneous", "path": "Miscellaneous", "value": 49639.857}, {"name": "Plastic or Rubber", "path": "Plastic or Rubber", "value": 101351.845}]