[{"name": "Capital goods", "path": "Capital goods", "value": 3232248.61}, {"name": "Consumer goods", "path": "Consumer goods", "value": 3463894.18}, {"name": "Intermediate goods", "path": "Intermediate goods", "value": 1599322.01}, {"name": "Mach and Elec", "path": "Mach and Elec", "value": 3242670.54}, {"name": "Metals", "path": "Metals", "value": 675789.67}, {"name": "Miscellaneous", "path": "Miscellaneous", "value": 358127.01}, {"name": "Plastic or Rubber", "path": "Plastic or Rubber", "value": 335132.35}]