[{"name": "Capital goods", "path": "Capital goods", "value": 24655.155}, {"name": "Consumer goods", "path": "Consumer goods", "value": 191218.642}, {"name": "Intermediate goods", "path": "Intermediate goods", "value": 326702.83}, {"name": "Mach and Elec", "path": "Mach and Elec", "value": 20195.095}, {"name": "Metals", "path": "Metals", "value": 5215.602}, {"name": "Miscellaneous", "path": "Miscellaneous", "value": 5105.624}, {"name": "Plastic or Rubber", "path": "Plastic or Rubber", "value": 4034.829}]